logo2cc/__init__.py
logo2cc/converter.py
logo2cc/setup.py
logo2cc-0.1.5.dist-info/LICENSE
logo2cc-0.1.5.dist-info/METADATA
logo2cc-0.1.5.dist-info/WHEEL
logo2cc-0.1.5.dist-info/top_level.txt
logo2cc-0.1.5.dist-info/RECORD
