Metadata-Version: 2.2
Name: logo2cc
Version: 0.1.5
Summary: Convert images to black and white (no gray) to use as custom logos on Stripe credit cards.
Home-page: https://github.com/VerisimilitudeX/logo2cc
Author: Piyush Acharya
Author-email: verisimilitude11@outlook.com
Classifier: Programming Language :: Python :: 3
Classifier: License :: OSI Approved :: MIT License
Classifier: Operating System :: OS Independent
Requires-Python: >=3.7
License-File: LICENSE
Requires-Dist: Pillow
Dynamic: author
Dynamic: author-email
Dynamic: classifier
Dynamic: description
Dynamic: description-content-type
Dynamic: home-page
Dynamic: requires-dist
Dynamic: requires-python
Dynamic: summary
